pwsync/__init__.py
pwsync/bw_cli_wrapper.py
pwsync/common.py
pwsync/console.py
pwsync/database_cli.py
pwsync/dataset.py
pwsync/gui.py
pwsync/item.py
pwsync/kp_db_cli.py
pwsync/main.py
pwsync/model.py
pwsync/sync.py
pwsync/version.py
pwsync-0.4b1.dist-info/LICENSE
pwsync-0.4b1.dist-info/METADATA
pwsync-0.4b1.dist-info/WHEEL
pwsync-0.4b1.dist-info/entry_points.txt
pwsync-0.4b1.dist-info/top_level.txt
pwsync-0.4b1.dist-info/RECORD
