Metadata-Version: 2.1
Name: pwsync
Version: 0.4b1
Summary: Synchronize password databases
Home-page: https://github.com/aptly-io/pwsync
Author: Francis Meyvis
Author-email: pwsync@mikmak.fun
License: GPL3
Classifier: Development Status :: 4 - Beta
Classifier: Programming Language :: Python :: 3.8
Classifier: License :: OSI Approved :: GNU General Public License v3 (GPLv3)
Classifier: Operating System :: POSIX :: Linux
Classifier: Topic :: Utilities
Classifier: Natural Language :: English
Classifier: Environment :: Console
Requires-Python: >=3.7.0
License-File: LICENSE
Requires-Dist: pykeepass (==4.0.3)
Requires-Dist: diffsync (==1.7.0)
Requires-Dist: prompt-toolkit (==3.0.38)
Provides-Extra: build
Requires-Dist: setuptools (>=45.0) ; extra == 'build'
Requires-Dist: wheel ; extra == 'build'
Requires-Dist: build ; extra == 'build'
Requires-Dist: twine ; extra == 'build'
Provides-Extra: dev
Requires-Dist: black ; extra == 'dev'
Requires-Dist: pylama[all] ; extra == 'dev'
Requires-Dist: pytest ; extra == 'dev'
Requires-Dist: pytest-cov ; extra == 'dev'
Requires-Dist: pytest-mock ; extra == 'dev'
Requires-Dist: pytz ; extra == 'dev'
Requires-Dist: types-python-dateutil ; extra == 'dev'
Requires-Dist: types-pytz ; extra == 'dev'
Requires-Dist: pre-commit ; extra == 'dev'
